{"list":[{"id":"dgd458gz2lDEm8BGr88t9","createdAt":"2021-12-29T20:36:22.164Z","title":"afasdf","author":"omoinminm","lead":"okmokim","content":"### Заголовок третьего уровня\r\n\r\n>Это пример цитаты,\r\nв которой угловая скобка\r\nставится только перед началом нового параграфа.\r\n>Второй параграф.\r\n\r\n- Проводник\r\n- Полупроводник\r\n- Диэлектрик"},{"id":"yBv75y5HHtT3-GGrUqBcg","createdAt":"2021-12-29T20:47:47.442Z","title":"nlknkln;;","author":"lknlknknlk","lead":";kn;kn;ln;n;n","content":";nlkn;n;on;opndf;ingianr"},{"id":"nl3Ui4fZObfcNWkVKeTnn","createdAt":"2021-12-29T20:48:00.689Z","title":"jbjkbukbdgf","author":"k","lead":";kbgkrjbg;j","content":"kjgbrjk;wgbw"}]}